[
  {
    "date": "2022-04-13",
    "home": "BRAVES",
    "road": "NATIONALS",
    "score": "1 - 3",
    "status": "FINAL"
  },
  {
    "date": "2022-04-13",
    "home": "REDS",
    "road": "GUARDIANS",
    "score": "3 - 7",
    "status": "FINAL"
  },
  {
    "date": "2022-04-13",
    "home": "PIRATES",
    "road": "CUBS",
    "score": "6 - 2",
    "status": "FINAL"
  },
  {
    "date": "2022-04-13",
    "home": "PHILLIES",
    "road": "METS",
    "score": "6 - 9",
    "status": "FINAL"
  },
  {
    "date": "2022-04-13",
    "home": "TWINS",
    "road": "DODGERS",
    "score": "0 - 7",
    "status": "FINAL"
  },
  {
    "date": "2022-04-13",
    "home": "TIGERS",
    "road": "RED SOX",
    "score": "7 - 9",
    "status": "FINAL"
  },
  {
    "date": "2022-04-13",
    "home": "DIAMONDBACKS",
    "road": "ASTROS",
    "score": "3 - 2",
    "status": "FINAL (10)"
  },
  {
    "date": "2022-04-13",
    "home": "GIANTS",
    "road": "PADRES",
    "score": "2 - 1",
    "status": "FINAL"
  },
  {
    "date": "2022-04-13",
    "home": "RAYS",
    "road": "ATHLETICS",
    "score": "2 - 4",
    "status": "FINAL"
  },
  {
    "date": "2022-04-13",
    "home": "YANKEES",
    "road": "BLUE JAYS",
    "score": "4 - 6",
    "status": "FINAL"
  },
  {
    "date": "2022-04-13",
    "home": "ORIOLES",
    "road": "BREWERS",
    "score": "2 - 4",
    "status": "FINAL"
  },
  {
    "date": "2022-04-13",
    "home": "WHITE SOX",
    "road": "MARINERS",
    "score": "6 - 4",
    "status": "FINAL"
  }
]